aiompesa/__init__.py
aiompesa/mpesa.py
aiompesa/utils.py
tests/__init__.py
tests/test_utils.py
aiompesa-0.0.4.dist-info/METADATA
aiompesa-0.0.4.dist-info/WHEEL
aiompesa-0.0.4.dist-info/top_level.txt
aiompesa-0.0.4.dist-info/RECORD
