Metadata-Version: 2.1
Name: aiompesa
Version: 0.0.4
Summary: A thin async wrapper of MPESA daraja API.
Home-page: http://github.com/musale/aiompesa
Author: Martin Musale
Author-email: martinmshale@gmail.com
License: MIT
Platform: UNKNOWN
Classifier: Programming Language :: Python :: 3
Classifier: License :: OSI Approved :: MIT License
Classifier: Operating System :: OS Independent
